st_dc/__init__.py
st_dc/dimensionality_reduction.py
st_dc/embedding_extractor.py
st_dc/visualizer.py
st_dc/viz.py
st_dc-1.1.4.dist-info/LICENSE.txt
st_dc-1.1.4.dist-info/METADATA
st_dc-1.1.4.dist-info/WHEEL
st_dc-1.1.4.dist-info/top_level.txt
st_dc-1.1.4.dist-info/RECORD
